{
  "days": [
    1,
    2,
    3,
    4,
    5,
    6,
    7,
    8,
    9,
    10,
    11,
    12,
    13,
    14,
    15,
    16,
    17,
    18,
    19
  ],
  "total_cost": 5600.0,
  "summary": [
    {
      "name": "Food",
      "displayName": "미식",
      "cost": 2400.0
    },
    {
      "name": "Transport",
      "displayName": "이동",
      "cost": 1400.0
    },
    {
      "name": "Sightseeing",
      "displayName": "관광",
      "cost": 800.0
    },
    {
      "name": "Accommodation",
      "displayName": "숙박",
      "cost": 1000.0
    }
  ],
  "stay_groups": [
    {
      "city": "Paris",
      "accommodation": "Cler Hôtel",
      "days": [
        1,
        2,
        3
      ]
    },
    {
      "city": "Lyon",
      "accommodation": "Airbnb (Presqu'île)",
      "days": [
        4,
        5
      ]
    },
    {
      "city": "Interlaken",
      "accommodation": "Hotel Interlaken",
      "days": [
        6,
        7
      ]
    },
    {
      "city": "Munich",
      "accommodation": "iQ Hotel Munchen",
      "days": [
        8,
        9
      ]
    },
    {
      "city": "Prague",
      "accommodation": "Prague Marriott",
      "days": [
        10,
        11
      ]
    },
    {
      "city": "Night Train",
      "accommodation": "Nightjet (Vienna-Venice)",
      "days": [
        12
      ]
    },
    {
      "city": "Venice",
      "accommodation": "Hotel Giovanelli",
      "days": [
        13
      ]
    },
    {
      "city": "Florence",
      "accommodation": "Hotel Spadai",
      "days": [
        14,
        15
      ]
    },
    {
      "city": "Rome",
      "accommodation": "The RomeHello",
      "days": [
        16,
        17,
        18
      ]
    },
    {
      "city": "Incheon",
      "accommodation": "기내",
      "days": [
        19
      ]
    }
  ],
  "total_points": [
    {
      "day": 1,
      "date": "2026-04-03",
      "time": "18:10",
      "activity": "Paris Arrival",
      "pos": [
        48.85,
        2.35
      ]
    },
    {
      "day": 4,
      "date": "2026-04-06",
      "time": "09:30",
      "activity": "Lyon Arrival",
      "pos": [
        45.7628,
        4.8332
      ]
    },
    {
      "day": 6,
      "date": "2026-04-08",
      "time": "11:30",
      "activity": "Interlaken Arrival",
      "pos": [
        46.68,
        7.86
      ]
    },
    {
      "day": 8,
      "date": "2026-04-10",
      "time": "11:30",
      "activity": "Munich Arrival",
      "pos": [
        48.13,
        11.57
      ]
    },
    {
      "day": 10,
      "date": "2026-04-12",
      "time": "11:30",
      "activity": "Prague Arrival",
      "pos": [
        50.08,
        14.43
      ]
    },
    {
      "day": 13,
      "date": "2026-04-15",
      "time": "08:34",
      "activity": "Venice Arrival",
      "pos": [
        45.44,
        12.32
      ]
    },
    {
      "day": 14,
      "date": "2026-04-16",
      "time": "11:30",
      "activity": "Florence Arrival",
      "pos": [
        43.77,
        11.25
      ]
    },
    {
      "day": 16,
      "date": "2026-04-18",
      "time": "11:30",
      "activity": "Rome Arrival",
      "pos": [
        41.9,
        12.49
      ]
    }
  ]
}